README.txt
setup.cfg
setup.py
RemOpenID.egg-info/PKG-INFO
RemOpenID.egg-info/SOURCES.txt
RemOpenID.egg-info/dependency_links.txt
RemOpenID.egg-info/entry_points.txt
RemOpenID.egg-info/namespace_packages.txt
RemOpenID.egg-info/not-zip-safe
RemOpenID.egg-info/paster_plugins.txt
RemOpenID.egg-info/requires.txt
RemOpenID.egg-info/top_level.txt
docs/HISTORY.txt
docs/INSTALL.txt
docs/LICENSE.GPL
docs/LICENSE.txt
topp/__init__.py
topp/remopenid/__init__.py
topp/remopenid/browser.py
topp/remopenid/complete.pt
topp/remopenid/configure.zcml
topp/remopenid/exportimport.zcml
topp/remopenid/plugin.py
topp/remopenid/profiles.zcml
topp/remopenid/setuphandlers.py
topp/remopenid/subscribers.py
topp/remopenid/tests.py
topp/remopenid/portlets/__init__.py
topp/remopenid/portlets/configure.zcml
topp/remopenid/portlets/member.pt
topp/remopenid/portlets/member.py
topp/remopenid/profiles/default/metadata.xml
topp/remopenid/profiles/default/portlets.xml
topp/remopenid/profiles/default/remopenid.txt
topp/remopenid/profiles/default/PAS/.objects
topp/remopenid/profiles/default/PAS/.preserve
topp/remopenid/profiles/default/PAS/borg_localroles.xml
topp/remopenid/profiles/default/PAS/chooser.xml
topp/remopenid/profiles/default/PAS/credentials_basic_auth.xml
topp/remopenid/profiles/default/PAS/credentials_cookie_auth.xml
topp/remopenid/profiles/default/PAS/local_roles.xml
topp/remopenid/profiles/default/PAS/membrane_groups.xml
topp/remopenid/profiles/default/PAS/membrane_properties.xml
topp/remopenid/profiles/default/PAS/membrane_roles.xml
topp/remopenid/profiles/default/PAS/membrane_user_factory.xml
topp/remopenid/profiles/default/PAS/membrane_users.xml
topp/remopenid/profiles/default/PAS/mutable_properties.xml
topp/remopenid/profiles/default/PAS/pluginregistry.xml
topp/remopenid/profiles/default/PAS/sniffer.xml
topp/remopenid/profiles/default/PAS/source_groups.xml
topp/remopenid/profiles/default/PAS/source_users.xml
topp/remopenid/profiles/default/PAS/user_factory.xml
topp/remopenid/www/openid.png
topp/remopenid/www/remopenidAdd.zpt