Metadata-Version: 1.0
Name: RemOpenID
Version: 0.9
Summary: Remember / OpenID integration
Home-page: https://svn.openplans.org/svn/topp.remopenid
Author: Rob Miller
Author-email: robm@openplans.org
License: GPL
Keywords: remember plone openid
Platform: UNKNOWN
Classifier: Framework :: Plone
Classifier: Programming Language :: Python
Classifier: Topic :: Software Development :: Libraries :: Python Modules
